malthus/__init__.py
malthus/birth.py
malthus/death.py
malthus/models.py
malthus-0.1.0.dist-info/LICENSE
malthus-0.1.0.dist-info/METADATA
malthus-0.1.0.dist-info/WHEEL
malthus-0.1.0.dist-info/RECORD
