Metadata-Version: 2.1
Name: malthus
Version: 0.1.0
Summary: Malthus is a Python library for building and running population models.
License: MIT
Author: George Alexander
Author-email: georgetucker.a@gmail.com
Requires-Python: >=3.9,<4.0
Classifier: License :: OSI Approved :: MIT License
Classifier: Programming Language :: Python :: 3
Classifier: Programming Language :: Python :: 3.9
Classifier: Programming Language :: Python :: 3.10
Classifier: Programming Language :: Python :: 3.11
